pytest_qanova/__init__.py
pytest_qanova/plugin.py
pytest_qanova-0.1.dist-info/LICENSE
pytest_qanova-0.1.dist-info/METADATA
pytest_qanova-0.1.dist-info/WHEEL
pytest_qanova-0.1.dist-info/entry_points.txt
pytest_qanova-0.1.dist-info/top_level.txt
pytest_qanova-0.1.dist-info/RECORD
