Metadata-Version: 2.1
Name: pytest_qanova
Version: 0.1
Summary: A pytest plugin to collect test information
Home-page: https://github.com/davidamirkhanyan/pytest-qanova
Author: Davit Amirkhanyan
Author-email: davit.amirkhanyan95@gmail.com
Classifier: Development Status :: 3 - Alpha
Classifier: Intended Audience :: Developers
Classifier: License :: OSI Approved :: MIT License
Classifier: Programming Language :: Python :: 3
Classifier: Programming Language :: Python :: 3.7
Classifier: Programming Language :: Python :: 3.8
Classifier: Programming Language :: Python :: 3.9
Classifier: Programming Language :: Python :: 3.10
Classifier: Framework :: Pytest
Requires-Python: >=3.6
License-File: LICENSE
Requires-Dist: pytest
